Agui/COMIC.TTF
Agui/Execute_Process.py
Agui/Show_Buttons.py
Agui/Text.py
Agui/Tools.py
Agui/Tools1.py
Agui/UserGui.py
Agui/__init__.py
Agui/bind.py
Agui/free.py
Agui/showTextFields.py
Agui-0.0.5.dist-info/LICENCE
Agui-0.0.5.dist-info/METADATA
Agui-0.0.5.dist-info/WHEEL
Agui-0.0.5.dist-info/top_level.txt
Agui-0.0.5.dist-info/RECORD
