Metadata-Version: 2.1
Name: Agui
Version: 0.0.5
Summary: A basic and quick gui application for python
Home-page: https://github.com/akicimusab/Agui
Author: Musab Akıcı
Author-email: musabakici8@gmail.com
License: UNKNOWN
Platform: UNKNOWN
Classifier: Programming Language :: Python :: 3
Classifier: License :: OSI Approved :: MIT License
Classifier: Operating System :: OS Independent
Requires-Python: >=3.6
